{
  "metadata": {
    "id": "aiostreams-🥖-2026-03-27.20-47-19-gpfrhz7",
    "name": "AIOStreams 🥖",
    "description": "Stremio avec une configuration optimisée pour la France !",
    "source": "external",
    "author": "valentinBoch",
    "version": "1.0.0",
    "category": "Debrid",
    "serviceRequired": false,
    "setToSaveInstallMenu": true
  },
  "config": {
    "trusted": false,
    "addonName": "AIOStreams 🥖",
    "addonDescription": "Stremio avec une configuration optimisée pour la France !",
    "excludedResolutions": [],
    "includedResolutions": [],
    "requiredResolutions": [],
    "preferredResolutions": [
      "2160p",
      "1440p",
      "1080p",
      "720p",
      "576p",
      "480p",
      "360p",
      "240p",
      "144p",
      "Unknown"
    ],
    "excludedQualities": [
      "CAM",
      "SCR",
      "TS",
      "TC"
    ],
    "includedQualities": [],
    "requiredQualities": [],
    "preferredQualities": [
      "BluRay REMUX",
      "BluRay",
      "WEB-DL",
      "WEBRip",
      "HDRip",
      "HC HD-Rip",
      "DVDRip",
      "HDTV",
      "CAM",
      "TS",
      "TC",
      "SCR",
      "Unknown"
    ],
    "excludedLanguages": [],
    "includedLanguages": [],
    "requiredLanguages": [
      "French",
      "Multi"
    ],
    "preferredLanguages": [
      "French"
    ],
    "excludedVisualTags": [
      "3D"
    ],
    "includedVisualTags": [],
    "requiredVisualTags": [],
    "preferredVisualTags": [],
    "excludedAudioTags": [],
    "includedAudioTags": [],
    "requiredAudioTags": [],
    "preferredAudioTags": [],
    "excludedAudioChannels": [],
    "includedAudioChannels": [],
    "requiredAudioChannels": [],
    "preferredAudioChannels": [],
    "excludedStreamTypes": [],
    "includedStreamTypes": [],
    "requiredStreamTypes": [],
    "preferredStreamTypes": [],
    "excludedEncodes": [
      "AV1"
    ],
    "includedEncodes": [],
    "requiredEncodes": [],
    "preferredEncodes": [],
    "excludedRegexPatterns": [],
    "includedRegexPatterns": [],
    "requiredRegexPatterns": [],
    "preferredRegexPatterns": [],
    "includedKeywords": [],
    "excludedKeywords": [
      "m2ts",
      ".m2ts",
      "iso",
      ".iso"
    ],
    "preferredKeywords": [],
    "excludeSeederRange": [
      0,
      1000
    ],
    "includeSeederRange": [
      0,
      1000
    ],
    "requiredSeederRange": [
      0,
      1000
    ],
    "seederRangeTypes": [],
    "ageRangeTypes": [
      "usenet"
    ],
    "digitalReleaseFilter": {
      "enabled": false,
      "tolerance": 1,
      "requestTypes": [
        "movie",
        "series",
        "anime"
      ],
      "addons": []
    },
    "excludeCachedFromAddons": [],
    "excludeCachedFromServices": [],
    "excludeCachedFromStreamTypes": [],
    "excludeUncached": false,
    "excludeUncachedFromAddons": [
      "739",
      "537"
    ],
    "excludeUncachedFromServices": [],
    "excludeUncachedFromStreamTypes": [],
    "excludeUncachedMode": "or",
    "excludedStreamExpressions": [],
    "requiredStreamExpressions": [],
    "preferredStreamExpressions": [],
    "includedStreamExpressions": [],
    "dynamicAddonFetching": {
      "enabled": true,
      "condition": "totalTimeTaken > 3000"
    },
    "groups": {
      "enabled": false,
      "groupings": []
    },
    "sortCriteria": {
      "global": [
        {
          "key": "cached",
          "direction": "desc"
        },
        {
          "key": "resolution",
          "direction": "desc"
        }
      ],
      "movies": [],
      "series": [],
      "anime": [],
      "cached": [
        {
          "key": "resolution",
          "direction": "desc"
        },
        {
          "key": "regexPatterns",
          "direction": "desc"
        },
        {
          "key": "size",
          "direction": "desc"
        }
      ],
      "uncached": [
        {
          "key": "resolution",
          "direction": "desc"
        },
        {
          "key": "regexPatterns",
          "direction": "desc"
        },
        {
          "key": "size",
          "direction": "desc"
        }
      ],
      "cachedMovies": [],
      "uncachedMovies": [],
      "cachedSeries": [],
      "uncachedSeries": [],
      "cachedAnime": [],
      "uncachedAnime": []
    },
    "posterService": "rpdb",
    "formatter": {
      "id": "custom",
      "definition": {
        "name": "{stream.proxied::istrue[\"🕵️ \"||\"\"]}{stream.type::=p2p[\"[P2P] \"||\"\"]}{service.shortName::exists[\"[{service.shortName}\"||\"\"]}{service.cached::istrue[\"⚡] \"||\"\"]}{service.cached::isfalse[\"💤] \"||\"\"]}{addon.name}{stream.library::istrue[\" (Your Media)\"||\"\"]} {stream.resolution::exists[\"{stream.resolution}\"||\"\"]}{stream.regexMatched::exists[\" ({stream.regexMatched})\"||\"\"]}",
        "description": "{stream.filename::exists[\"🎬\"||\"\"]} {stream.filename::exists[\"{stream.filename}\"||\"\"]} \n{stream.quality::exists[\"🎥 {stream.quality} \"||\"\"]}{stream.encode::exists[\"🎞️ {stream.encode} \"||\"\"]}{stream.releaseGroup::exists[\"🏷️ {stream.releaseGroup}\"||\"\"]}\n{stream.size::>0[\"📦 {stream.size::bytes} \"||\"\"]}{stream.folderSize::>0[\"/ 📦 {stream.folderSize::bytes}\"||\"\"]}{stream.duration::>0[\"⏱️ {stream.duration::time} \"||\"\"]}{stream.seeders::>0[\"👥 {stream.seeders} \"||\"\"]}{stream.age::exists[\"📅 {stream.age} \"||\"\"]}{stream.indexer::exists[\"🔍 {stream.indexer}\"||\"\"]}\n{stream.languages::exists[\"🌎 {stream.languages::join(' | ')}\"||\"\"]}\n{stream.filename::exists[\"📁\"||\"\"]} {stream.folderName::exists[\"{stream.folderName}/\"||\"\"]}{stream.filename::exists[\"{stream.filename}\"||\"\"]}\n{stream.visualTags::exists[\"📺 {stream.visualTags::join(' | ')} \"||\"\"]}{stream.audioTags::exists[\"🎧 {stream.audioTags::join(' | ')} \"||\"\"]}{stream.audioChannels::exists[\"🔊 {stream.audioChannels::join(' | ')}\"||\"\"]}"
      }
    },
    "proxy": {
      "id": "mediaflow",
      "proxiedAddons": [],
      "proxiedServices": []
    },
    "resultLimits": {
      "global": 30,
      "resolution": 15
    },
    "size": {
      "global": {
        "movies": [
          0,
          37000000000
        ]
      }
    },
    "hideErrors": false,
    "hideErrorsForResources": [],
    "statistics": {
      "enabled": true,
      "statsToShow": [
        "addon",
        "filter"
      ]
    },
    "tmdbAccessToken": "<template_placeholder>",
    "tmdbApiKey": "<template_placeholder>",
    "yearMatching": {
      "enabled": true,
      "tolerance": 1,
      "strict": false,
      "requestTypes": [],
      "addons": []
    },
    "titleMatching": {
      "mode": "exact",
      "similarityThreshold": 0.2,
      "enabled": true,
      "requestTypes": [],
      "addons": []
    },
    "seasonEpisodeMatching": {
      "enabled": true,
      "strict": true,
      "requestTypes": [],
      "addons": []
    },
    "deduplicator": {
      "enabled": true,
      "excludeAddons": [],
      "multiGroupBehaviour": "aggressive",
      "keys": [
        "filename",
        "infoHash",
        "smartDetect"
      ],
      "cached": "single_result",
      "uncached": "disabled",
      "p2p": "disabled"
    },
    "autoPlay": {
      "enabled": true,
      "attributes": [
        "service",
        "proxied",
        "resolution",
        "quality",
        "encode",
        "audioTags",
        "visualTags",
        "languages",
        "releaseGroup"
      ]
    },
    "areYouStillThere": {
      "enabled": false
    },
    "precacheNextEpisode": false,
    "services": [
      {
        "id": "torbox",
        "enabled": true,
        "credentials": {}
      },
      {
        "id": "realdebrid",
        "enabled": false,
        "credentials": {}
      },
      {
        "id": "alldebrid",
        "enabled": false,
        "credentials": {}
      },
      {
        "id": "premiumize",
        "enabled": false,
        "credentials": {}
      },
      {
        "id": "debridlink",
        "enabled": false,
        "credentials": {}
      },
      {
        "id": "stremio_nntp",
        "enabled": false,
        "credentials": {}
      },
      {
        "id": "nzbdav",
        "enabled": false,
        "credentials": {}
      },
      {
        "id": "altmount",
        "enabled": false,
        "credentials": {}
      },
      {
        "id": "offcloud",
        "enabled": false,
        "credentials": {}
      },
      {
        "id": "putio",
        "enabled": false,
        "credentials": {}
      },
      {
        "id": "easynews",
        "enabled": false,
        "credentials": {}
      },
      {
        "id": "easydebrid",
        "enabled": false,
        "credentials": {}
      },
      {
        "id": "debrider",
        "enabled": false,
        "credentials": {}
      },
      {
        "id": "pikpak",
        "enabled": false,
        "credentials": {}
      },
      {
        "id": "seedr",
        "enabled": false,
        "credentials": {}
      },
      {
        "id": "stremthru_newz",
        "enabled": false,
        "credentials": {}
      }
    ],
    "presets": [
      {
        "type": "comet",
        "instanceId": "811",
        "enabled": true,
        "options": {
          "name": "Comet (ru)",
          "timeout": 15000,
          "resources": [
            "stream"
          ],
          "includeP2P": false,
          "removeTrash": true,
          "mediaTypes": []
        }
      },
      {
        "type": "stremthruTorz",
        "instanceId": "a0f",
        "enabled": true,
        "options": {
          "name": "StremThru Torz",
          "timeout": 15000,
          "resources": [
            "stream"
          ],
          "url": "https://stremthru.13377001.xyz/stremio/torz",
          "mediaTypes": [],
          "includeP2P": false,
          "useMultipleInstances": false
        }
      },
      {
        "type": "stremthruStore",
        "instanceId": "f35",
        "enabled": true,
        "options": {
          "name": "StremThru Store",
          "timeout": 15000,
          "resources": [
            "stream"
          ],
          "url": "https://stremthru.13377001.xyz/stremio/store",
          "mediaTypes": [],
          "usenet": false
        }
      },
      {
        "type": "mediafusion",
        "instanceId": "132",
        "enabled": true,
        "options": {
          "name": "MediaFusion",
          "timeout": 15000,
          "resources": [
            "stream"
          ],
          "useCachedResultsOnly": true,
          "enableWatchlistCatalogs": false,
          "downloadViaBrowser": false,
          "contributorStreams": false,
          "certificationLevelsFilter": [],
          "nudityFilter": [],
          "mediaTypes": [],
          "url": "https://mediafusionfortheweebs.midnightignite.me"
        }
      }
    ],
    "catalogModifications": [
      {
        "id": "d88791b.recently_added_movies",
        "type": "movie",
        "name": "YGGtorrent - Récemment Ajoutés",
        "shuffle": false,
        "enabled": true,
        "usePosterService": false,
        "hideable": true,
        "searchable": false,
        "addonName": "StreamFusion"
      },
      {
        "id": "d88791b.recently_added_tv_shows",
        "type": "series",
        "name": "YGGtorrent - Récemment Ajoutées",
        "shuffle": false,
        "enabled": true,
        "usePosterService": false,
        "hideable": true,
        "searchable": false,
        "addonName": "StreamFusion"
      }
    ],
    "externalDownloads": false,
    "cacheAndPlay": {
      "streamTypes": []
    },
    "checkOwned": true
  }
}
